mseep_nautex-0.2.21.dist-info/licenses/LICENSE
nautex/__init__.py
nautex/cli.py
nautex/agent_setups/__init__.py
nautex/agent_setups/base.py
nautex/agent_setups/claude.py
nautex/agent_setups/codex.py
nautex/agent_setups/cursor.py
nautex/agent_setups/files_based_mcp.py
nautex/agent_setups/opencode.py
nautex/agent_setups/section_managed_rules_mixin.py
nautex/api/__init__.py
nautex/api/api_models.py
nautex/api/client.py
nautex/api/scope_context_model.py
nautex/api/test_client.py
nautex/models/__init__.py
nautex/models/config.py
nautex/models/integration_status.py
nautex/models/mcp.py
nautex/models/plan_context.py
nautex/prompts/common_workflow.py
nautex/prompts/consts.py
nautex/services/__init__.py
nautex/services/agent_rules_service.py
nautex/services/config_service.py
nautex/services/document_service.py
nautex/services/integration_status_service.py
nautex/services/mcp_config_service.py
nautex/services/mcp_service.py
nautex/services/nautex_api_service.py
nautex/services/section_managed_file_service.py
nautex/services/ui_service.py
nautex/tui/__init__.py
nautex/tui/styles.py
nautex/tui/screens/__init__.py
nautex/tui/screens/setup_screen.py
nautex/tui/widgets/__init__.py
nautex/tui/widgets/config_dialogs.py
nautex/tui/widgets/dialogs.py
nautex/tui/widgets/info_help_dialog.py
nautex/tui/widgets/inputs.py
nautex/tui/widgets/integration.py
nautex/tui/widgets/integration_status.py
nautex/tui/widgets/loadable_list.py
nautex/tui/widgets/plan_context.py
nautex/tui/widgets/system_info.py
nautex/tui/widgets/views.py
nautex/utils/__init__.py
nautex/utils/mcp_toml_utils.py
nautex/utils/mcp_utils.py
nautex/utils/opencode_config_utils.py
mseep_nautex-0.2.21.dist-info/METADATA
mseep_nautex-0.2.21.dist-info/WHEEL
mseep_nautex-0.2.21.dist-info/entry_points.txt
mseep_nautex-0.2.21.dist-info/top_level.txt
mseep_nautex-0.2.21.dist-info/RECORD
